[
  {
    "product__name": "\n            OPPO Find X8 5G 16GB/512GB\n        ",
    "price": "22.990.000₫"
  },
  {
    "product__name": "\n            OPPO Find X8 Pro 5G 16GB/512GB\n        ",
    "price": "29.990.000₫"
  },
  {
    "product__name": "\n            HONOR Magic V3 5G 12GB/512GB\n                Mẫu mới\n        ",
    "price": "39.990.000₫"
  },
  {
    "img": "https://cdn.tgdd.vn/Products/Images/42/332234/realme-c75-gold-thumb-600x600.jpg",
    "product__name": "\n            realme C75\n                Mẫu mới\n        ",
    "price": "5.690.000₫"
  },
  {
    "product__name": "",
    "price": ""
  },
  {
    "product__name": "",
    "price": ""
  },
  {
    "product__name": "",
    "price": ""
  },
  {
    "img": "https://cdn.tgdd.vn/Products/Images/42/329149/iphone-16-pro-max-sa-mac-thumb-600x600.jpg",
    "product__name": "\n            iPhone 16 Pro Max\n        ",
    "price": "34.590.000₫"
  },
  {
    "product__name": "",
    "price": ""
  },
  {
    "product__name": "",
    "price": ""
  },
  {
    "product__name": "",
    "price": ""
  },
  {
    "img": "https://cdn.tgdd.vn/Products/Images/42/329143/iphone-16-pro-titan-sa-mac.png",
    "product__name": "\n            iPhone 16 Pro\n        ",
    "price": "28.590.000₫"
  },
  {
    "product__name": "",
    "price": ""
  },
  {
    "product__name": "",
    "price": ""
  },
  {
    "product__name": "",
    "price": ""
  },
  {
    "product__name": "",
    "price": ""
  },
  {
    "img": "https://cdn.tgdd.vn/Products/Images/42/329138/iphone-16-plus-xanh-thumb-600x600.jpg",
    "product__name": "\n            iPhone 16 Plus\n        ",
    "price": "25.990.000₫"
  },
  {
    "product__name": "",
    "price": ""
  },
  {
    "product__name": "",
    "price": ""
  },
  {
    "product__name": "",
    "price": ""
  },
  {
    "img": "https://cdn.tgdd.vn/Products/Images/42/329135/iphone-16-blue-600x600.png",
    "product__name": "\n            iPhone 16\n        ",
    "price": "22.490.000₫"
  },
  {
    "product__name": "",
    "price": ""
  },
  {
    "product__name": "",
    "price": ""
  },
  {
    "product__name": "",
    "price": ""
  },
  {
    "img": "https://cdn.tgdd.vn/Products/Images/42/307174/samsung-galaxy-s24-ultra-grey-thumbnew-600x600.jpg",
    "product__name": "\n            Samsung Galaxy S24 Ultra 5G\n        ",
    "price": "29.990.000₫"
  },
  {
    "product__name": "",
    "price": ""
  },
  {
    "product__name": "",
    "price": ""
  },
  {
    "img": "https://cdn.tgdd.vn/Products/Images/42/331207/samsung-galaxy-a16-green-thumbnew-600x600.jpg",
    "product__name": "\n            Samsung Galaxy A16\n        ",
    "price": "5.690.000₫"
  },
  {
    "product__name": "",
    "price": ""
  },
  {
    "product__name": "",
    "price": ""
  },
  {
    "img": "https://cdn.tgdd.vn/Products/Images/42/331204/samsung-galaxy-a16-5g-gold-thumbnew-600x600.jpg",
    "product__name": "\n            Samsung Galaxy A16 5G\n        ",
    "price": "6.990.000₫"
  },
  {
    "product__name": "",
    "price": ""
  },
  {
    "product__name": "",
    "price": ""
  },
  {
    "img": "https://cdn.tgdd.vn/Products/Images/42/329938/xiaomi-14t-grey-thumb-600x600.jpg",
    "product__name": "\n            Xiaomi 14T 5G\n        ",
    "price": "12.990.000₫"
  },
  {
    "product__name": "",
    "price": ""
  },
  {
    "product__name": "",
    "price": ""
  },
  {
    "product__name": "\n            vivo V40 5G 12GB/256GB\n                Mẫu mới\n        ",
    "price": "12.990.000₫"
  },
  {
    "product__name": "\n            vivo V40 Lite 8GB/256GB\n        ",
    "price": "8.190.000₫"
  },
  {
    "img": "https://cdn.tgdd.vn/Products/Images/42/314206/xiaomi-redmi-note-13-green-thumb-600x600.jpg",
    "product__name": "\n            Xiaomi Redmi Note 13 Pro\n        ",
    "price": "5.790.000₫"
  },
  {
    "product__name": "",
    "price": ""
  },
  {
    "product__name": "",
    "price": ""
  },
  {
    "product__name": "\n            OPPO Reno12 5G 12GB/256GB Hồng\n        ",
    "price": "11.490.000₫"
  },
  {
    "img": "https://cdn.tgdd.vn/Products/Images/42/327190/oppo-reno12-f-5g-orange-thumb-600x600.jpg",
    "product__name": "\n            OPPO Reno12 F 5G\n        ",
    "price": "8.990.000₫"
  },
  {
    "product__name": "",
    "price": ""
  },
  {
    "product__name": "",
    "price": ""
  },
  {
    "img": "https://cdn.tgdd.vn/Products/Images/42/325800/redmi-13-blue-thumb-600x600.jpg",
    "product__name": "\n            Xiaomi Redmi 13\n        ",
    "price": "3.890.000₫"
  },
  {
    "product__name": "",
    "price": ""
  },
  {
    "product__name": "",
    "price": ""
  },
  {
    "img": "https://cdn.tgdd.vn/Products/Images/42/328449/oppo-a3x-red-thumb-600x600.jpg",
    "product__name": "\n            OPPO A3x\n        ",
    "price": "3.290.000₫"
  },
  {
    "product__name": "",
    "price": ""
  },
  {
    "product__name": "",
    "price": ""
  },
  {
    "product__name": "",
    "price": ""
  },
  {
    "img": "https://cdn.tgdd.vn/Products/Images/42/328752/samsung-galaxy-a06-blue-thumb-1-600x600.jpg",
    "product__name": "\n            Samsung Galaxy A06\n        ",
    "price": "3.090.000₫"
  },
  {
    "product__name": "",
    "price": ""
  },
  {
    "product__name": "",
    "price": ""
  },
  {
    "product__name": "",
    "price": ""
  }
]